wheecode/__init__.py
wheecode/footer.txt
wheecode/header.txt
wheecode/main.py
wheecode/matrix.py
wheecode/printer.py
wheecode/profilometer_parse.py
wheecode/utils.py
wheecode/devices/__init__.py
wheecode/devices/base_serial_device.py
wheecode/devices/efd_pico_pulse.py
wheecode/devices/efd_pressure_box.py
wheecode/devices/keyence_line_scanner.py
wheecode/devices/keyence_micrometer.py
wheecode/devices/keyence_profilometer.py
wheecode-0.5.0.dist-info/LICENSE
wheecode-0.5.0.dist-info/METADATA
wheecode-0.5.0.dist-info/WHEEL
wheecode-0.5.0.dist-info/top_level.txt
wheecode-0.5.0.dist-info/RECORD
