Metadata-Version: 2.1
Name: wheecode
Version: 0.5.0
Summary: Simple GCode generator
Home-page: https://github.com/xloem/wheecode
Download-URL: https://github.com/xloem/wheecode/tarball/main
Author: Wheeeeeeeee!!
Author-email: 0xloem@gmail.com
Keywords: gcode,3dprinting,cnc,reprap,additive
License-File: LICENSE
Requires-Dist: numpy
Requires-Dist: solidpython (<0.3)
Requires-Dist: matplotlib (<3.0)
Requires-Dist: pyserial
Requires-Dist: vpython (<7.6) ; python_version < "3"
Requires-Dist: vpython (>=7.6) ; python_version >= "3"
